akinator/__init__.py
akinator/akinator.py
akinator/enums.py
akinator/exceptions.py
akinator/types.py
py_akinator-0.0.1.dist-info/LICENSE
py_akinator-0.0.1.dist-info/METADATA
py_akinator-0.0.1.dist-info/WHEEL
py_akinator-0.0.1.dist-info/top_level.txt
py_akinator-0.0.1.dist-info/RECORD
