Metadata-Version: 2.1
Name: py-akinator
Version: 0.0.1
Summary: A Python library for interacting with the Akinator game API
Author-email: Rio <contact@devrio.org>
License: MIT License
Project-URL: Homepage, https://github.com/DevsCommons/akinator-py
Project-URL: Bug Tracker, https://github.com/DevsCommons/akinator-py/issues
Keywords: akinator,game,api,async
Classifier: Development Status :: 3 - Alpha
Classifier: Intended Audience :: Developers
Classifier: License :: OSI Approved :: MIT License
Classifier: Operating System :: OS Independent
Classifier: Programming Language :: Python :: 3
Classifier: Programming Language :: Python :: 3.6
Classifier: Programming Language :: Python :: 3.7
Classifier: Programming Language :: Python :: 3.8
Classifier: Programming Language :: Python :: 3.9
Requires-Python: >=3.6
License-File: LICENSE
Requires-Dist: requests
Requires-Dist: aiohttp
Requires-Dist: beautifulsoup4
